{
  "letter": "147",
  "slug": "letter-147",
  "sent": {
    "date": {
      "text": "Darmstadt, Ende März 1776",
      "when": null,
      "notBefore": "1776-03-28",
      "notAfter": "1776-03-31",
      "from": null,
      "to": null,
      "cert": null
    },
    "locations": [
      {
        "ref": "20",
        "cert": null,
        "erschlossen": null,
        "label": "Darmstadt",
        "resolved": {
          "index": "20",
          "name": "Darmstadt",
          "ref": "http://d-nb.info/gnd/4011077-1"
        }
      }
    ],
    "persons": [
      {
        "ref": "1",
        "cert": null,
        "erschlossen": null,
        "label": "Jakob Michael Reinhold Lenz",
        "resolved": {
          "index": "1",
          "name": "Jakob Michael Reinhold Lenz",
          "vorname": "Jakob Michael Reinhold",
          "nachname": "Lenz",
          "komm": "jmr-lenz",
          "ref": "https://d-nb.info/gnd/118571656"
        }
      }
    ]
  },
  "received": {
    "date": null,
    "locations": [
      {
        "ref": "7",
        "cert": null,
        "erschlossen": null,
        "label": "Straßburg",
        "resolved": {
          "index": "7",
          "name": "Straßburg",
          "ref": "http://d-nb.info/gnd/4057878-1"
        }
      }
    ],
    "persons": [
      {
        "ref": "15",
        "cert": null,
        "erschlossen": null,
        "label": "Luise König",
        "resolved": {
          "index": "15",
          "name": "Luise König",
          "vorname": "Luise",
          "nachname": "König",
          "komm": "könig",
          "ref": null
        }
      }
    ]
  },
  "hasOriginal": true,
  "isProofread": true,
  "isDraft": true,
  "hasText": true,
  "hasTraditions": true,
  "hasSidenotes": true,
  "pageCount": 2,
  "pages": [
    "1",
    "2"
  ],
  "traditionsHtml": "<section class=\"traditions\" data-letter=\"147\">\n   <div class=\"tradition-app\" data-ref=\"4\">\n      <div class=\"lb-line-block\" data-type=\"break\">\n\t\t\t\tKraków, Biblioteka Jagiellońska, Lenziana 5, Nr. 18. Entwurf in Bleistift.\n\t\t\t</div>\n   </div>\n</section>"
}
