{
  "1": [],
  "2": [
    {
      "id": "letter-066-page-2-sidenote-1",
      "order": 1,
      "letter": "66",
      "page": "2",
      "pos": "left",
      "annotation": "am linken Rand der zweiten Seite, vertikal",
      "html": "<aside class=\"sidenote\" id=\"letter-066-page-2-sidenote-1\" data-letter=\"66\" data-page=\"2\" data-pos=\"left\" data-annotation=\"am linken Rand der zweiten Seite, vertikal\">\n   <div class=\"lb-line-block\" data-type=\"break\" data-tab=\"1\">Auch Goethen sag nichts davon, diesmal laß uns was alleine thun. Desto mehr Freude\n      hat er dran wenn er überrascht wird. Ich hab ihm geschrieben ich arbeitete – aber\n      nicht was?</div>\n</aside>"
    },
    {
      "id": "letter-066-page-2-sidenote-2",
      "order": 2,
      "letter": "66",
      "page": "2",
      "pos": "bottom",
      "annotation": "am unteren Rand der zweiten Seite",
      "html": "<aside class=\"sidenote\" id=\"letter-066-page-2-sidenote-2\" data-letter=\"66\" data-page=\"2\" data-pos=\"bottom\" data-annotation=\"am unteren Rand der zweiten Seite\">\n   <div class=\"lb-line-block\" data-type=\"break\" data-align=\"center\"><span class=\"gr\">παντα δε δυναμενα δια την πισιν.</span></div>\n</aside>"
    }
  ],
  "3": [],
  "4": []
}
