<?xml version="1.0" encoding="utf-8"?>
<opus>
	<descriptions>
		<letterDesc letter="1">
			<date value="Dorpat (Tartu), 2. Januar 1765" />
			<sort value="1765-01-02" />
			<location ref="1" />
			<senders>
				<sender ref="1" />
			</senders>
			<receivers>
				<receiver ref="2" />
			</receivers>
			<hasOriginal value="true" />
			<isProofread value="true" />
			<isDraft value="false" />
		</letterDesc>
		<letterDesc letter="2">
			<date value="Tarwast (Tarvastu), 11. Oktober 1767" />
			<sort value="1767-10-11" />
			<location ref="2" />
			<senders>
				<sender ref="1" />
			</senders>
			<receivers>
				<receiver ref="3" />
			</receivers>
			<hasOriginal value="true" />
			<isProofread value="true" />
			<isDraft value="false" />
		</letterDesc>

		<letterDesc letter="3">
			<date value="Tarwast (Tarvastu), 9. November 1767" />
			<sort value="1767-11-09" />
			<location ref="2" />
			<senders>
				<sender ref="1" />
			</senders>
			<receivers>
				<receiver ref="4" />
				<receiver ref="5" />
			</receivers>
			<hasOriginal value="true" />
			<isProofread value="true" />
			<isDraft value="false" />
		</letterDesc>

		<letterDesc letter="4">
			<date value="Tarwast (Tarvastu), 24. November 1767" />
			<sort value="1767-11-24" />
			<location ref="2" />
			<senders>
				<sender ref="1" />
				<sender ref="3" />
			</senders>
			<receivers>
				<receiver ref="4" />
			</receivers>
			<hasOriginal value="true" />
			<isProofread value="true" />
			<isDraft value="false" />
		</letterDesc>

		<letterDesc letter="5">
			<date value="Tarwast (Tarvastu), nach 24. Januar 1768" />
			<sort value="1767-11-24" notBefore="1767-11-24" />
			<location ref="1" />
			<senders>
				<sender ref="1" />
				<sender ref="7" />
			</senders>
			<receivers>
				<receiver ref="3" />
				<receiver ref="6" />
			</receivers>
			<hasOriginal value="true" />
			<isProofread value="true" />
			<isDraft value="false" />
		</letterDesc>

		<letterDesc letter="6">
			<date value="Königsberg (Kaliningrad), 14. Oktober 1769" />
			<sort value="1769-10-14" />
			<location ref="3" />
			<senders>
				<sender ref="1" />
			</senders>
			<receivers>
				<receiver ref="5" />
			</receivers>
			<hasOriginal value="true" />
			<isProofread value="true" />
			<isDraft value="false" />
		</letterDesc>

		<letterDesc letter="7">
			<date value="Dorpat (Tartu), wahrscheinlich Mitte 1770" />
			<sort value="1770-06-15" notBefore="1770-06-01" notAfter="1770-07-01" />
			<location ref="1" />
			<senders>
				<sender ref="5" />
			</senders>
			<receivers>
				<receiver ref="1" />
				<receiver ref="8" />
			</receivers>
			<hasOriginal value="false" />
			<isProofread value="true" />
			<isDraft value="true" />
		</letterDesc>

		<letterDesc letter="8">
			<date value="Fort Louis, Ende Mai 1772" />
			<sort value="1772-05-28" notBefore="1772-05-15" notAfter="1772-05-30" />
			<location ref="4" />
			<senders>
				<sender ref="1" />
			</senders>
			<receivers>
				<receiver ref="9" />
			</receivers>
			<hasOriginal value="false" />
			<isProofread value="true" />
			<isDraft value="false" />
		</letterDesc>

		<letterDesc letter="9">
			<date value="Fort Louis, 3. Juni 1772" />
			<sort value="1772-06-02" />
			<location ref="4" />
			<senders>
				<sender ref="1" />
			</senders>
			<receivers>
				<receiver ref="9" />
			</receivers>
			<hasOriginal value="false" />
			<isProofread value="true" />
			<isDraft value="false" />
		</letterDesc>

		<letterDesc letter="10">
			<date value="Fort Louis, 10. Juni 1772" />
			<sort value="1772-06-10" />
			<location ref="4" />
			<senders>
				<sender ref="1" />
			</senders>
			<receivers>
				<receiver ref="9" />
			</receivers>
			<hasOriginal value="false" />
			<isProofread value="true" />
			<isDraft value="false" />
		</letterDesc>

		<letterDesc letter="11">
			<date value="Fort Louis, 15. Juni 1772" />
			<sort value="1772-06-15" />
			<location ref="4" />
			<senders>
				<sender ref="1" />
			</senders>
			<receivers>
				<receiver ref="4" />
			</receivers>
			<hasOriginal value="true" />
			<isProofread value="true" />
			<isDraft value="false" />
		</letterDesc>
		
		<letterDesc letter="12">
			<date value="Fort Louis, 28. Juni 1772" />
			<sort value="1772-06-28" />
			<location ref="4" />
			<senders>
				<sender ref="1" />
			</senders>
			<receivers>
				<receiver ref="9" />
			</receivers>
			<hasOriginal value="true" />
			<isProofread value="true" />
			<isDraft value="false" />
		</letterDesc>
		
		<letterDesc letter="13">
			<date value="Fort Louis, 13. Juli 1772" />
			<sort value="1772-07-13" />
			<location ref="4" />
			<senders>
				<sender ref="1" />
			</senders>
			<receivers>
				<receiver ref="8" />
			</receivers>
			<hasOriginal value="true" />
			<isProofread value="true" />
			<isDraft value="false" />
		</letterDesc>
		
		<letterDesc letter="14">
			<date value="Fort Louis, Anfang August 1772" />
			<sort value="1772-08-01" />
			<location ref="4" />
			<senders>
				<sender ref="1" />
			</senders>
			<receivers>
				<receiver ref="9" />
			</receivers>
			<hasOriginal value="true" />
			<isProofread value="true" />
			<isDraft value="false" />
		</letterDesc>
		
		<letterDesc letter="15">
			<date value="Fort Louis, Mitte August 1772" />
			<sort value="1772-08-15" />
			<location ref="4" />
			<senders>
				<sender ref="1" />
			</senders>
			<receivers>
				<receiver ref="9" />
			</receivers>
			<hasOriginal value="true" />
			<isProofread value="true" />
			<isDraft value="false" />
		</letterDesc>
		
		<letterDesc letter="16">
			<date value="Fort Louis, 31. August 1772" />
			<sort value="1772-08-31" />
			<location ref="4" />
			<senders>
				<sender ref="1" />
			</senders>
			<receivers>
				<receiver ref="9" />
			</receivers>
			<hasOriginal value="true" />
			<isProofread value="true" />
			<isDraft value="false" />
		</letterDesc>
		
		<letterDesc letter="17">
			<date value="Weisenburg, 2. September und 2. Oktober 1772" />
			<sort value="1772-09-02" />
			<sort value="1772-10-02" />
			<location ref="6" />
			<senders>
				<sender ref="1" />
			</senders>
			<receivers>
				<receiver ref="4" />
			</receivers>
			<hasOriginal value="true" />
			<isProofread value="true" />
			<isDraft value="false" />
		</letterDesc>
		<letterDesc letter="18">
				<date value="Landau, 7. September 1772" />
				<sort value="1772-09-07" />
				<location ref="5" />
				<senders>
					<sender ref="1" />
				</senders>
				<receivers>
					<receiver ref="9" />
				</receivers>
				<hasOriginal value="true" />
				<isProofread value="true" />
				<isDraft value="false" />
			</letterDesc>
			
		<letterDesc letter="19">
				<date value="Landau, 18. September 1772" />
				<sort value="1772-09-18" />
				<location ref="5" />
				<senders>
					<sender ref="1" />
				</senders>
				<receivers>
					<receiver ref="9" />
				</receivers>
				<hasOriginal value="true" />
				<isProofread value="true" />
				<isDraft value="false" />
		</letterDesc>
			
		<letterDesc letter="20">
				<date value="Arensburg (Kuressaare), 24. September 1772" />
				<sort value="1772-09-24" />
				<location ref="10" />
				<senders>
					<sender ref="8" />
				</senders>
				<receivers>
					<receiver ref="1" />
				</receivers>
				<hasOriginal value="true" />
				<isProofread value="true" />
				<isDraft value="false" />
		</letterDesc>
			
		<letterDesc letter="21">
				<date value="Landau, Anfang Oktober 1772" />
				<sort value="1772-10-05" />
				<location ref="5" />
				<senders>
					<sender ref="1" />
				</senders>
				<receivers>
					<receiver ref="9" />
				</receivers>
				<hasOriginal value="true" />
				<isProofread value="true" />
				<isDraft value="false" />
		</letterDesc>
			
		<letterDesc letter="22">
				<date value="Landau, vor Mitte Oktober 1772" />
				<sort value="1772-10-10" />
				<location ref="5" />
				<senders>
					<sender ref="1" />
				</senders>
				<receivers>
					<receiver ref="9" />
				</receivers>
				<hasOriginal value="true" />
				<isProofread value="true" />
				<isDraft value="false" />
		</letterDesc>
			
		<letterDesc letter="23">
			<date value="Landau, Mitte Oktober 1772" />
			<sort value="1772-10-15" />
			<location ref="5" />
			<senders>
				<sender ref="1" />
			</senders>
			<receivers>
				<receiver ref="9" />
			</receivers>
			<hasOriginal value="true" />
			<isProofread value="true" />
			<isDraft value="false" />
		</letterDesc>
		
		<letterDesc letter="24">
			<date value="Landau, Zweite Oktoberhälfte Oktober 1772" />
			<sort value="1772-10-20" />
			<location ref="5" />
			<senders>
				<sender ref="1" />
			</senders>
			<receivers>
				<receiver ref="9" />
			</receivers>
			<hasOriginal value="true" />
			<isProofread value="true" />
			<isDraft value="false" />
		</letterDesc>
		
		<letterDesc letter="25">
			<date value="Landau, Gegen Ende Oktober 1772" />
			<sort value="1772-10-25" />
			<location ref="5" />
			<senders>
				<sender ref="1" />
			</senders>
			<receivers>
				<receiver ref="9" />
			</receivers>
			<hasOriginal value="true" />
			<isProofread value="true" />
			<isDraft value="false" />
		</letterDesc>
		
		<letterDesc letter="26">
			<date value="Landau, Ende Oktober 1772" />
			<sort value="1772-10-31" />
			<location ref="5" />
			<senders>
				<sender ref="1" />
			</senders>
			<receivers>
				<receiver ref="9" />
			</receivers>
			<hasOriginal value="true" />
			<isProofread value="true" />
			<isDraft value="false" />
		</letterDesc>
		
		<letterDesc letter="27"> <!-- Handelt es sich hier um einen Entwurf? -->
			<date value="Landau, 10. Dezember 1772" />
			<sort value="1772-12-10" />
			<location ref="5" />
			<senders>
				<sender ref="1" />
			</senders>
			<receivers>
				<receiver ref="4" />
			</receivers>
			<hasOriginal value="true" />
			<isProofread value="true" />
			<isDraft value="false" />
		</letterDesc>
		
		<letterDesc letter="28">
			<date value="Straßburg, Mitte März 1774" />
			<sort value="1774-03-15" />
			<location ref="7" />
			<senders>
				<sender ref="1" />
			</senders>
			<receivers>
				<receiver ref="10" />
			</receivers>
			<hasOriginal value="true" />
			<isProofread value="true" />
			<isDraft value="false" />
		</letterDesc>
		
		<letterDesc letter="29">
			<date value="Straßburg, Ende März 1774" />
			<sort value="1774-03-31" />
			<location ref="7" />
			<senders>
				<sender ref="1" />
			</senders>
			<receivers>
				<receiver ref="10" />
			</receivers>
			<hasOriginal value="true" />
			<isProofread value="true" />
			<isDraft value="false" />
		</letterDesc>
		
		<letterDesc letter="30">
			<date value="Zürich, 22. April 1774" />
			<sort value="1774-04-22" />
			<location ref="11" />
			<senders>
				<sender ref="10" />
			</senders>
			<receivers>
				<receiver ref="1" />
				<receiver ref="11" />
			</receivers>
			<hasOriginal value="true" />
			<isProofread value="true" />
			<isDraft value="false" />
		</letterDesc>
		
		<letterDesc letter="31">
			<date value="Zürich, 10. Mai 1774" />
			<sort value="1774-05-10" />
			<location ref="11" />
			<senders>
				<sender ref="10" />
			</senders>
			<receivers>
				<receiver ref="1" />
			</receivers>
			<hasOriginal value="true" />
			<isProofread value="true" />
			<isDraft value="false" />
		</letterDesc>
		
		<letterDesc letter="32">
			<date value="Zürich, Ende Mai 1774" />
			<sort value="1774-05-31" />
			<location ref="11" />
			<senders>
				<sender ref="10" />
			</senders>
			<receivers>
				<receiver ref="1" />
				<receiver ref="11" />
			</receivers>
			<hasOriginal value="false" />
			<isProofread value="true" />
			<isDraft value="true" />
		</letterDesc>
		
		<letterDesc letter="33">
			<date value="Straßburg, Anfang Juni 1774" />
			<sort value="1774-06-01" />
			<location ref="7" />
			<senders>
				<sender ref="1" />
				<sender ref="11" />
			</senders>
			<receivers>
				<receiver ref="10" />
			</receivers>
			<hasOriginal value="true" />
			<isProofread value="true" />
			<isDraft value="false" />
		</letterDesc>
		
		<letterDesc letter="34">
			<date value="Zürich, 11. Juni 1774" />
			<sort value="1774-06-11" />
			<location ref="11" />
			<senders>
				<sender ref="10" />
			</senders>
			<receivers>
				<receiver ref="1" />
				<receiver ref="11" />
			</receivers>
			<hasOriginal value="true" />
			<isProofread value="true" />
			<isDraft value="false" />
		</letterDesc>
		
		<letterDesc letter="35">
			<date value="Zürich, 14. Juni 1774" />
			<sort value="1774-06-14" />
			<location ref="11" />
			<senders>
				<sender ref="10" />
			</senders>
			<receivers>
				<receiver ref="1" />
				<receiver ref="11" />
			</receivers>
			<hasOriginal value="true" />
			<isProofread value="true" />
			<isDraft value="false" />
		</letterDesc>
		
		<letterDesc letter="36">
			<date value="Straßburg, 18. Juni 1774" />
			<sort value="1774-06-18" />
			<location ref="7" />
			<senders>
				<sender ref="1" />
				<sender ref="11" />
			</senders>
			<receivers>
				<receiver ref="10" />
			</receivers>
			<hasOriginal value="true" />
			<isProofread value="true" />
			<isDraft value="false" />
		</letterDesc>
		
		<letterDesc letter="37">
			<date value="Straßburg, Mitte Juli 1774" />
			<sort value="1774-07-15" />
			<location ref="7" />
			<senders>
				<sender ref="10" />
			</senders>
			<receivers>
				<receiver ref="12" />
			</receivers>
			<hasOriginal value="false" />
			<isProofread value="true" />
			<isDraft value="false" />
		</letterDesc>
		
		<letterDesc letter="38">
			<date value="Zürich, 31. August 1774" />
			<sort value="1774-08-31" />
			<location ref="11" />
			<senders>
				<sender ref="23" />
			</senders>
			<receivers>
				<receiver ref="1" />
			</receivers>
			<hasOriginal value="true" />
			<isProofread value="true" />
			<isDraft value="false" />
		</letterDesc>
		
		<letterDesc letter="39">
			<date value="Zürich, 2. September 1774" />
			<sort value="1774-09-02" />
			<location ref="11" />
			<senders>
				<sender ref="10" />
			</senders>
			<receivers>
				<receiver ref="1" />
			</receivers>
			<hasOriginal value="false" />
			<isProofread value="true" />
			<isDraft value="false" />
		</letterDesc>
		
		<letterDesc letter="40">
			<date value="Straßburg, 7. November 1774" />
			<sort value="1774-11-04" />
			<location ref="7" />
			<senders>
				<sender ref="1" />
			</senders>
			<receivers>
				<receiver ref="8" />
			</receivers>
			<hasOriginal value="true" />
			<isProofread value="true" />
			<isDraft value="false" />
		</letterDesc>
		
		<letterDesc letter="41">
			<date value="Straßburg, Februar 1775" />
			<sort value="1775-02-01" />
			<location ref="7" />
			<senders>
				<sender ref="1" />
			</senders>
			<receivers>
				<receiver ref="12" />
			</receivers>
			<hasOriginal value="true" />
			<isProofread value="true" />
			<isDraft value="false" />
		</letterDesc>
		
		<letterDesc letter="42">
			<date value="Straßburg, 8. April 1775" />
			<sort value="1775-04-08" />
			<location ref="7" />
			<senders>
				<sender ref="1" />
			</senders>
			<receivers>
				<receiver ref="10" />
			</receivers>
			<hasOriginal value="true" />
			<isProofread value="true" />
			<isDraft value="false" />
		</letterDesc>
		
		<letterDesc letter="43">
			<date value="Zürich, 14. April 1775" />
			<sort value="1775-04-14" />
			<location ref="11" />
			<senders>
				<sender ref="10" />
			</senders>
			<receivers>
				<receiver ref="11" />
			</receivers>
			<hasOriginal value="false" />
			<isProofread value="true" />
			<isDraft value="false" />
		</letterDesc>
		
		<letterDesc letter="44">
			<date value="Zürich, 20. April 1775" />
			<sort value="1775-04-20" />
			<location ref="11" />
			<senders>
				<sender ref="10" />
			</senders>
			<receivers>
				<receiver ref="1" />
			</receivers>
			<hasOriginal value="true" />
			<isProofread value="true" />
			<isDraft value="false" />
		</letterDesc>
		
		<letterDesc letter="45">
			<date value="Straßburg, Ende April 1775" />
			<sort value="1775-04-30" />
			<location ref="7" />
			<senders>
				<sender ref="1" />
			</senders>
			<receivers>
				<receiver ref="10" />
			</receivers>
			<hasOriginal value="true" />
			<isProofread value="true" />
			<isDraft value="false" />
		</letterDesc>
		
		<letterDesc letter="46">
			<date value="Straßburg, 1. Mai 1775" />
			<sort value="1775-05-01" />
			<location ref="7" />
			<senders>
				<sender ref="1" />
			</senders>
			<receivers>
				<receiver ref="13" />
			</receivers>
			<hasOriginal value="true" />
			<isProofread value="true" />
			<isDraft value="false" />
		</letterDesc>
		
		<letterDesc letter="47">
			<date value="Emmeningen, Anfang Mai 1775" />
			<sort value="1775-05-03" />
			<location ref="12" />
			<senders>
				<sender ref="18" />
			</senders>
			<receivers>
				<receiver ref="1" />
			</receivers>
			<hasOriginal value="true" />
			<isProofread value="true" />
			<isDraft value="false" />
		</letterDesc>
		
		<letterDesc letter="48">
			<date value="Straßburg, Anfang Mai 1775" />
			<sort value="1775-05-05" />
			<location ref="7" />
			<senders>
				<sender ref="1" />
			</senders>
			<receivers>
				<receiver ref="10" />
			</receivers>
			<hasOriginal value="true" />
			<isProofread value="true" />
			<isDraft value="false" />
		</letterDesc>
		
		<letterDesc letter="49">
			<date value="Straßburg, 10. Mai 1775" />
			<sort value="1775-05-10" />
			<location ref="7" />
			<senders>
				<sender ref="1" />
			</senders>
			<receivers>
				<receiver ref="14" />
			</receivers>
			<hasOriginal value="true" />
			<isProofread value="true" />
			<isDraft value="false" />
		</letterDesc>
		
		<letterDesc letter="50">
			<date value="Straßburg, 20. Mai 1775" />
			<sort value="1775-05-20" />
			<location ref="7" />
			<senders>
				<sender ref="1" />
			</senders>
			<receivers>
				<receiver ref="13" />
			</receivers>
			<hasOriginal value="false" />
			<isProofread value="true" />
			<isDraft value="false" />
		</letterDesc>
		
		<letterDesc letter="51">
			<date value="Straßburg, Wahrscheinlich Juni 1775" />
			<sort value="1775-06-01" />
			<location ref="7" />
			<senders>
				<sender ref="1" />
			</senders>
			<receivers>
				<receiver ref="10" />
			</receivers>
			<hasOriginal value="false" />
			<isProofread value="true" />
			<isDraft value="false" /> <!-- Handelt es sich hier um einen Entwurf? -->
		</letterDesc>
		
		<letterDesc letter="52">
			<date value="Straßburg, Wahrscheinlich Anfang Juni 1775" />
			<sort value="1775-06-07" />
			<location ref="7" />
			<senders>
				<sender ref="1" />
			</senders>
			<receivers>
				<receiver ref="15" />
			</receivers>
			<hasOriginal value="true" />
			<isProofread value="true" />
			<isDraft value="false" />
		</letterDesc>
		
		<letterDesc letter="53">
			<date value="Straßburg, Juni 1775" />
			<sort value="1775-06-15" />
			<location ref="7" />
			<senders>
				<sender ref="1" />
			</senders>
			<receivers>
				<receiver ref="13" />
			</receivers>
			<hasOriginal value="true" />
			<isProofread value="true" />
			<isDraft value="false" />
		</letterDesc>
		
		<letterDesc letter="54"> <!-- Französischer Brief -->
			<date value="Straßburg, Wahrscheinlich Juni 1775" />
			<sort value="1775-06-20" />
			<location ref="7" />
			<senders>
				<sender ref="1" />
			</senders>
			<receivers>
				<receiver ref="12" />
			</receivers>
			<hasOriginal value="true" />
			<isProofread value="true" />
			<isDraft value="false" />
		</letterDesc>
		
		<letterDesc letter="55">
			<date value="Straßburg, 13. Juli 1775" />
			<sort value="1775-07-13" />
			<location ref="7" />
			<senders>
				<sender ref="1" />
				<sender ref="15" />
			</senders>
			<receivers>
				<receiver ref="16" />
			</receivers>
			<hasOriginal value="true" />
			<isProofread value="true" />
			<isDraft value="false" />
		</letterDesc>
		
		<letterDesc letter="56">
			<date value="Wahrscheinlich Straßburg, Juli 1775" />
			<sort value="1775-07-15" />
			<location ref="7" />
			<senders>
				<sender ref="1" />
				<sender ref="10" />
			</senders>
			<receivers>
				<receiver ref="19" />
			</receivers>
			<hasOriginal value="true" />
			<isProofread value="true" />
			<isDraft value="false" />
		</letterDesc>
		
		<letterDesc letter="57">
			<date value="Straßburg, Juli 1775" />
			<sort value="1775-07-17" />
			<location ref="7" />
			<senders>
				<sender ref="1" />
			</senders>
			<receivers>
				<receiver ref="13" />
			</receivers>
			<hasOriginal value="false" />
			<isProofread value="true" />
			<isDraft value="false" />
		</letterDesc>
		
		<letterDesc letter="58">
			<date value="Zürich, 22. Juli 1775" />
			<sort value="1775-07-22" />
			<location ref="11" />
			<senders>
				<sender ref="10" />
			</senders>
			<receivers>
				<receiver ref="1" />
			</receivers>
			<hasOriginal value="true" />
			<isProofread value="true" />
			<isDraft value="false" />
		</letterDesc>
		
		<letterDesc letter="59">
			<date value="Straßburg, 23. Juli 1775" />
			<sort value="1775-07-23" />
			<location ref="7" />
			<senders>
				<sender ref="1" />
			</senders>
			<receivers>
				<receiver ref="17" />
			</receivers>
			<hasOriginal value="true" />
			<isProofread value="true" />
			<isDraft value="false" />
		</letterDesc>
		
		<letterDesc letter="60">
			<date value="Straßburg, Juli 1775" />
			<sort value="1775-07-25" />
			<location ref="7" />
			<senders>
				<sender ref="1" />
			</senders>
			<receivers>
				<receiver ref="13" />
			</receivers>
			<hasOriginal value="false" />
			<isProofread value="true" />
			<isDraft value="false" />
		</letterDesc>
		
		<letterDesc letter="61">
			<date value="Straßburg, Juli 1775" />
			<sort value="1775-07-28" />
			<location ref="7" />
			<senders>
				<sender ref="1" />
			</senders>
			<receivers>
				<receiver ref="10" />
			</receivers>
			<hasOriginal value="true" />
			<isProofread value="true" />
			<isDraft value="false" />
		</letterDesc>
		
		<letterDesc letter="62">
			<date value="Straßburg, 29. Juli 1775" />
			<sort value="1775-07-29" />
			<location ref="7" />
			<senders>
				<sender ref="1" />
			</senders>
			<receivers>
				<receiver ref="10" />
			</receivers>
			<hasOriginal value="true" />
			<isProofread value="true" />
			<isDraft value="false" />
		</letterDesc>
		
		<letterDesc letter="63">
			<date value="Straßburg, 31. Juli 1775" />
			<sort value="1775-07-31" />
			<location ref="7" />
			<senders>
				<sender ref="1" />
			</senders>
			<receivers>
				<receiver ref="13" />
			</receivers>
			<hasOriginal value="false" />
			<isProofread value="true" />
			<isDraft value="false" />
		</letterDesc>
		
		<letterDesc letter="64">
			<date value="Straßburg, 28. August 1775" />
			<sort value="1775-08-28" />
			<location ref="7" />
			<senders>
				<sender ref="1" />
			</senders>
			<receivers>
				<receiver ref="16" />
			</receivers>
			<hasOriginal value="true" />
			<isProofread value="true" />
			<isDraft value="false" />
		</letterDesc>
		
		<letterDesc letter="65">
			<date value="Straßburg, 3. September 1775" />
			<sort value="1775-09-03" />
			<location ref="7" />
			<senders>
				<sender ref="1" />
			</senders>
			<receivers>
				<receiver ref="10" />
			</receivers>
			<hasOriginal value="true" />
			<isProofread value="true" />
			<isDraft value="false" />
		</letterDesc>
		
		<letterDesc letter="66">
			<date value="Straßburg, Mitte September 1775" />
			<sort value="1775-09-10" />
			<location ref="7" />
			<senders>
				<sender ref="1" />
			</senders>
			<receivers>
				<receiver ref="10" />
			</receivers>
			<hasOriginal value="true" />
			<isProofread value="true" />
			<isDraft value="false" />
		</letterDesc>
		
		<letterDesc letter="67">
			<date value="Tartu, September 1775" />
			<sort value="1775-09-14" />
			<location ref="1" />
			<senders>
				<sender ref="5" />
			</senders>
			<receivers>
				<receiver ref="1" />
			</receivers>
			<hasOriginal value="true" />
			<isProofread value="true" />
			<isDraft value="false" />
		</letterDesc>
		
		<letterDesc letter="68">
			<date value="Straßburg, September 1775" />
			<sort value="1775-09-15" />
			<location ref="7" />
			<senders>
				<sender ref="1" />
			</senders>
			<receivers>
				<receiver ref="13" />
			</receivers>
			<hasOriginal value="false" />
			<isProofread value="true" />
			<isDraft value="false" />
		</letterDesc>
		
		<letterDesc letter="69">
			<date value="Straßburg, 29. September 1775" />
			<sort value="1775-09-29" />
			<location ref="7" />
			<senders>
				<sender ref="1" />
			</senders>
			<receivers>
				<receiver ref="17" />
			</receivers>
			<hasOriginal value="true" />
			<isProofread value="true" />
			<isDraft value="false" />
		</letterDesc>
		
		<letterDesc letter="70">
			<date value="Straßburg, 29. September 1775" />
			<sort value="1775-09-29" />
			<location ref="7" />
			<senders>
				<sender ref="1" />
			</senders>
			<receivers>
				<receiver ref="10" />
			</receivers>
			<hasOriginal value="true" />
			<isProofread value="true" />
			<isDraft value="false" />
		</letterDesc>
		
		<letterDesc letter="71">
			<date value="Straßburg, 30. September 1775" />
			<sort value="1775-09-30" />
			<location ref="7" />
			<senders>
				<sender ref="1" />
			</senders>
			<receivers>
				<receiver ref="17" />
			</receivers>
			<hasOriginal value="true" />
			<isProofread value="true" />
			<isDraft value="false" />
		</letterDesc>
		
		<letterDesc letter="72">
			<date value="Straßburg, Ende September 1775" />
			<sort value="1775-09-30" />
			<location ref="7" />
			<senders>
				<sender ref="1" />
			</senders>
			<receivers>
				<receiver ref="10" />
			</receivers>
			<hasOriginal value="true" />
			<isProofread value="true" />
			<isDraft value="false" />
		</letterDesc>
		
		<letterDesc letter="73">
			<date value="Straßburg, Wahrscheinlich Oktober 1775" />
			<sort value="1775-10-01" />
			<location ref="7" />
			<senders>
				<sender ref="1" />
			</senders>
			<receivers>
				<receiver ref="18" />
			</receivers>
			<hasOriginal value="true" />
			<isProofread value="true" />
			<isDraft value="false" />
		</letterDesc>
		
		<letterDesc letter="74">
			<date value="Kehl, 2. Oktober 1775" />
			<sort value="1775-10-2" />
			<location ref="9" />
			<senders>
				<sender ref="1" />
			</senders>
			<receivers>
				<receiver ref="20" />
			</receivers>
			<hasOriginal value="true" />
			<isProofread value="true" />
			<isDraft value="false" />
		</letterDesc>
		
		<letterDesc letter="75">
			<date value="Zürich, Oktober 1775" />
			<sort value="1775-10-05" />
			<location ref="11" />
			<senders>
				<sender ref="10" />
			</senders>
			<receivers>
				<receiver ref="1" />
			</receivers>
			<hasOriginal value="true" />
			<isProofread value="true" />
			<isDraft value="false" />
		</letterDesc>
		
		<letterDesc letter="76">
			<date value="Straßburg, 13. Oktober 1775" />
			<sort value="1775-10-13" />
			<location ref="7" />
			<senders>
				<sender ref="1" />
			</senders>
			<receivers>
				<receiver ref="21" />
			</receivers>
			<hasOriginal value="true" />
			<isProofread value="true" />
			<isDraft value="false" />
		</letterDesc>
		
		<letterDesc letter="77">
			<date value="Straßburg, Oktober 1775" />
			<sort value="1775-10-15" />
			<location ref="7" />
			<senders>
				<sender ref="1" />
			</senders>
			<receivers>
				<receiver ref="35" />
			</receivers>
			<hasOriginal value="true" />
			<isProofread value="true" />
			<isDraft value="false" />
		</letterDesc>
		
		<letterDesc letter="78">
			<date value="Straßburg, 23. Oktober 1775" />
			<sort value="1775-10-23" />
			<location ref="7" />
			<senders>
				<sender ref="1" />
			</senders>
			<receivers>
				<receiver ref="14" />
			</receivers>
			<hasOriginal value="true" />
			<isProofread value="true" />
			<isDraft value="false" />
		</letterDesc>
		
		<letterDesc letter="79">
			<date value="Ulm, 13. November 1775" />
			<sort value="1775-11-13" />
			<location ref="13" />
			<senders>
				<sender ref="22" />
			</senders>
			<receivers>
				<receiver ref="1" />
			</receivers>
			<hasOriginal value="true" />
			<isProofread value="true" />
			<isDraft value="false" />
		</letterDesc>
		
		<letterDesc letter="80">
			<date value="Straßburg, 15. November 1775" />
			<sort value="1775-11-15" />
			<location ref="7" />
			<senders>
				<sender ref="1" />
			</senders>
			<receivers>
				<receiver ref="20" />
			</receivers>
			<hasOriginal value="true" />
			<isProofread value="true" />
			<isDraft value="false" />
		</letterDesc>
		
		<letterDesc letter="81">
			<date value="Straßburg, 18. November 1775" />
			<sort value="1775-11-18" />
			<location ref="7" />
			<senders>
				<sender ref="1" />
			</senders>
			<receivers>
				<receiver ref="17" />
			</receivers>
			<hasOriginal value="true" />
			<isProofread value="true" />
			<isDraft value="false" />
		</letterDesc>
		
		<letterDesc letter="82">
			<date value="Straßburg, 18. November 1775" />
			<sort value="1775-11-18" />
			<location ref="7" />
			<senders>
				<sender ref="1" />
			</senders>
			<receivers>
				<receiver ref="4" />
			</receivers>
			<hasOriginal value="false" />
			<isProofread value="true" />
			<isDraft value="false" />
		</letterDesc>
		
		<letterDesc letter="83">
			<date value="Straßburg, 20. November 1775" />
			<sort value="1775-11-20" />
			<location ref="7" />
			<senders>
				<sender ref="1" />
			</senders>
			<receivers>
				<receiver ref="17" />
			</receivers>
			<hasOriginal value="true" />
			<isProofread value="true" />
			<isDraft value="false" />
		</letterDesc>
		
		<letterDesc letter="84">
			<date value="Straßburg, November 1775" />
			<sort value="1775-11-25" />
			<location ref="7" />
			<senders>
				<sender ref="1" />
			</senders>
			<receivers>
				<receiver ref="20" />
			</receivers>
			<hasOriginal value="true" />
			<isProofread value="true" />
			<isDraft value="false" />
		</letterDesc>
		
		<letterDesc letter="85">
			<date value="Straßburg, Ende November 1775" />
			<sort value="1775-11-30" />
			<location ref="7" />
			<senders>
				<sender ref="1" />
			</senders>
			<receivers>
				<receiver ref="14" />
			</receivers>
			<hasOriginal value="true" />
			<isProofread value="true" />
			<isDraft value="false" />
		</letterDesc>
		
		<letterDesc letter="86">
			<date value="Straßburg, Dezember 1775" />
			<sort value="1775-12-01" />
			<location ref="7" />
			<senders>
				<sender ref="1" />
			</senders>
			<receivers>
				<receiver ref="14" />
			</receivers>
			<hasOriginal value="true" />
			<isProofread value="true" />
			<isDraft value="false" />
		</letterDesc>
		
		<letterDesc letter="87">
			<date value="Straßburg, Dezember 1775" />
			<sort value="1775-12-05" />
			<location ref="7" />
			<senders>
				<sender ref="1" />
			</senders>
			<receivers>
				<receiver ref="22" />
			</receivers>
			<hasOriginal value="true" />
			<isProofread value="true" />
			<isDraft value="false" />
		</letterDesc>
		
		<letterDesc letter="88">
			<date value="Straßburg, Dezember 1775" />
			<sort value="1775-12-15" />
			<location ref="7" />
			<senders>
				<sender ref="1" />
			</senders>
			<receivers>
				<receiver ref="20" />
			</receivers>
			<hasOriginal value="true" />
			<isProofread value="true" />
			<isDraft value="false" />
		</letterDesc>
		
		<letterDesc letter="89">
			<date value="Straßburg, Dezember 1775" />
			<sort value="1775-12-20" />
			<location ref="7" />
			<senders>
				<sender ref="1" />
			</senders>
			<receivers>
				<receiver ref="20" />
			</receivers>
			<hasOriginal value="true" />
			<isProofread value="true" />
			<isDraft value="false" />
		</letterDesc>
		
		<letterDesc letter="90">
			<date value="Straßburg, Dezember 1775" />
			<sort value="1775-12-21" />
			<location ref="7" />
			<senders>
				<sender ref="1" />
			</senders>
			<receivers>
				<receiver ref="17" />
			</receivers>
			<hasOriginal value="true" />
			<isProofread value="true" />
			<isDraft value="false" />
		</letterDesc>
		
		<letterDesc letter="91">
			<date value="Straßburg, 25. Dezember 1775" />
			<sort value="1775-12-25" />
			<location ref="7" />
			<senders>
				<sender ref="1" />
				<sender ref="12" />
				<sender ref="18" />
			</senders>
			<receivers>
				<receiver ref="19" />
			</receivers>
			<hasOriginal value="true" />
			<isProofread value="true" />
			<isDraft value="false" />
		</letterDesc>
		
		<letterDesc letter="92">
			<date value="Straßburg, 28. Dezember 1775" />
			<sort value="1775-12-28" />
			<location ref="7" />
			<senders>
				<sender ref="1" />
			</senders>
			<receivers>
				<receiver ref="13" />
			</receivers>
			<hasOriginal value="true" />
			<isProofread value="true" />
			<isDraft value="false" />
		</letterDesc>
		
		<letterDesc letter="93">
			<date value="Gotha, 2. Januar 1776" />
			<sort value="1776-01-02" />
			<location ref="15" />
			<senders>
				<sender ref="14" />
			</senders>
			<receivers>
				<receiver ref="1" />
			</receivers>
			<hasOriginal value="true" />
			<isProofread value="true" />
			<isDraft value="false" />
		</letterDesc>
		
		<letterDesc letter="94">
			<date value="Straßburg, 2. Januar 1776" />
			<sort value="1776-01-02" />
			<location ref="7" />
			<senders>
				<sender ref="1" />
			</senders>
			<receivers>
				<receiver ref="35" />
			</receivers>
			<hasOriginal value="true" />
			<isProofread value="true" />
			<isDraft value="false" />
		</letterDesc>
		
		<letterDesc letter="95">
			<date value="Zürich, Januar 1776" />
			<sort value="1776-01-09" />
			<location ref="11" />
			<senders>
				<sender ref="22" />
			</senders>
			<receivers>
				<receiver ref="1" />
			</receivers>
			<hasOriginal value="true" />
			<isProofread value="true" />
			<isDraft value="false" />
		</letterDesc>
		
		<letterDesc letter="96">
			<date value="Göttingen, 10. Januar 1776" />
			<sort value="1776-01-10" />
			<location ref="16" />
			<senders>
				<sender ref="20" />
			</senders>
			<receivers>
				<receiver ref="1" />
			</receivers>
			<hasOriginal value="true" />
			<isProofread value="true" />
			<isDraft value="false" />
		</letterDesc>
		
		<letterDesc letter="97">
			<date value="Emmendingen , 13. Januar 1776" />
			<sort value="1776-01-13" />
			<location ref="12" />
			<senders>
				<sender ref="18" />
			</senders>
			<receivers>
				<receiver ref="1" />
			</receivers>
			<hasOriginal value="true" />
			<isProofread value="true" />
			<isDraft value="false" />
		</letterDesc>
		
		<letterDesc letter="98">
			<date value="Zürich, 14. Januar 1776" />
			<sort value="1776-01-14" />
			<location ref="11" />
			<senders>
				<sender ref="10" /><!-- Dieser Brief ist von Lavaters Schreiber geschrieben worden. -->
			</senders>
			<receivers>
				<receiver ref="1" />
			</receivers>
			<hasOriginal value="true" />
			<isProofread value="true" />
			<isDraft value="false" />
		</letterDesc>
		
		<letterDesc letter="99">
			<date value="Kehl, 14. Januar 1776" />
			<sort value="1776-01-14" />
			<location ref="9" />
			<senders>
				<sender ref="1" />
			</senders>
			<receivers>
				<receiver ref="14" />
			</receivers>
			<hasOriginal value="true" />
			<isProofread value="true" />
			<isDraft value="true" />
		</letterDesc>
		
		<letterDesc letter="100">
			<date value="Kehl, Januar 1776" />
			<sort value="1776-01-15" />
			<location ref="9" />
			<senders>
				<sender ref="1" />
			</senders>
			<receivers>
				<receiver ref="19" />
			</receivers>
			<hasOriginal value="true" />
			<isProofread value="true" />
			<isDraft value="false" /><!-- Teile des Briefs sind auf französisch geschrieben. -->
		</letterDesc>
		
		<letterDesc letter="101">
			<date value="Straßburg, Wahrscheinlich Januar 1776" />
			<sort value="1776-01-16" />
			<location ref="7" />
			<senders>
				<sender ref="1" />
			</senders>
			<receivers>
				<receiver ref="11" />
			</receivers>
			<hasOriginal value="true" />
			<isProofread value="true" />
			<isDraft value="false" />
		</letterDesc>
		
		<letterDesc letter="102">
			<date value="Straßburg, Januar 1776" />
			<sort value="1776-01-17" />
			<location ref="7" />
			<senders>
				<sender ref="1" />
			</senders>
			<receivers>
				<receiver ref="10" />
			</receivers>
			<hasOriginal value="true" />
			<isProofread value="true" />
			<isDraft value="false" />
		</letterDesc>
		
		<letterDesc letter="103">
			<date value="Straßburg, 21./22. Januar 1776" />
			<sort value="1776-01-21" notBefore="1776-01-21" notAfter="1776-01-22" />
			<location ref="7" />
			<senders>
				<sender ref="1" />
			</senders>
			<receivers>
				<receiver ref="20" />
			</receivers>
			<hasOriginal value="true" />
			<isProofread value="true" />
			<isDraft value="false" />
		</letterDesc>
		
		<letterDesc letter="104">
			<date value="Zürich, 24. Januar 1776" />
			<sort value="1776-01-24" />
			<location ref="11" />
			<senders>
				<sender ref="10" />
			</senders>
			<receivers>
				<receiver ref="1" />
			</receivers>
			<hasOriginal value="false" />
			<isProofread value="true" />
			<isDraft value="false" />
		</letterDesc>
		
		<letterDesc letter="105">
			<date value="Straßburg, Januar 1776" />
			<sort value="1776-01-30" />
			<location ref="7" />
			<senders>
				<sender ref="1" />
			</senders>
			<receivers>
				<receiver ref="26" />
			</receivers>
			<hasOriginal value="true" />
			<isProofread value="true" />
			<isDraft value="true" />
		</letterDesc>
		
		<letterDesc letter="106">
			<date value="Straßburg, Ende Januar 1776" />
			<sort value="1776-01-31" />
			<location ref="7" />
			<senders>
				<sender ref="1" />
			</senders>
			<receivers>
				<receiver ref="10" />
			</receivers>
			<hasOriginal value="true" />
			<isProofread value="true" />
			<isDraft value="true" />
		</letterDesc>
		
		<letterDesc letter="107">
			<date value="Kopenhagen, 3. Februar 1776" />
			<sort value="1776-02-03" />
			<location ref="17" />
			<senders>
				<sender ref="27" />
			</senders>
			<receivers>
				<receiver ref="1" />
			</receivers>
			<hasOriginal value="true" />
			<isProofread value="true" />
			<isDraft value="false" />
		</letterDesc>
		
		<letterDesc letter="108">
			<date value="Straßburg, 12. Februar 1776" />
			<sort value="1776-02-12" />
			<location ref="7" />
			<senders>
				<sender ref="1" />
			</senders>
			<receivers>
				<receiver ref="20" />
			</receivers>
			<hasOriginal value="true" />
			<isProofread value="true" />
			<isDraft value="false" />
		</letterDesc>
		
		<letterDesc letter="109">
			<date value="Straßburg, Vor 15. Februar 1776" />
			<sort value="1776-02-08" />
			<location ref="7" />
			<senders>
				<sender ref="1" />
			</senders>
			<receivers>
				<receiver ref="20" />
			</receivers>
			<hasOriginal value="true" />
			<isProofread value="true" />
			<isDraft value="false" />
		</letterDesc>
		
		<letterDesc letter="110">
			<date value="Auf dem Weg von Hannover nach Kassel?, 9. Februar 1776" />
			<sort value="1776-02-09" />
			<location ref="NN" />
			<senders>
				<sender ref="19" />
			</senders>
			<receivers>
				<receiver ref="1" />
			</receivers>
			<hasOriginal value="true" />
			<isProofread value="true" />
			<isDraft value="false" />
		</letterDesc>
		
		<letterDesc letter="111">
			<date value="Auf dem Weg von Hannover nach Kassel?, Februar 1776" />
			<sort value="1776-02-12" />
			<location ref="NN" />
			<senders>
				<sender ref="19" />
			</senders>
			<receivers>
				<receiver ref="1" />
			</receivers>
			<hasOriginal value="true" />
			<isProofread value="true" />
			<isDraft value="false" />
		</letterDesc>
		
	</descriptions>
</opus>
